ecl_twitter
